README.txt
setup.cfg
setup.py
doc/Makefile
doc/contents.rst
doc/make.bat
doc/model.dot
doc/source/ChangeLog.rst
doc/source/conf.py
doc/source/index.rst
doc/source/quickstart.rst
doc/source/references.rst
src/pymeigo/__init__.py
src/pymeigo/funcs.py
src/pymeigo/init.py
src/pymeigo/meigo.py
src/pymeigo/wrapper_meigo.py
src/pymeigo.egg-info/PKG-INFO
src/pymeigo.egg-info/SOURCES.txt
src/pymeigo.egg-info/dependency_links.txt
src/pymeigo.egg-info/requires.txt
src/pymeigo.egg-info/top_level.txt
test/__init__.py
test/test_R_example.py
test/test_funcs.py
test/test_import.py
test/test_meigo.py
test/test_wrapper_meigo.py